src/__init__.py
src/aal.py
macaal-0.0.3.dist-info/LICENSE
macaal-0.0.3.dist-info/METADATA
macaal-0.0.3.dist-info/WHEEL
macaal-0.0.3.dist-info/entry_points.txt
macaal-0.0.3.dist-info/top_level.txt
macaal-0.0.3.dist-info/RECORD
