Metadata-Version: 2.2
Name: macaal
Version: 0.0.3
Summary: Auto Assembly Linker - for MacOS M-Series, ARM64
Home-page: https://github.com/Silicon27/aal
Author: Silicon27
Author-email: yangsilicon@gmail.com
Classifier: Programming Language :: Python :: 3
Classifier: License :: OSI Approved :: MIT License
Classifier: Operating System :: OS Independent
Requires-Python: >=3.6
License-File: LICENSE
Dynamic: author
Dynamic: author-email
Dynamic: classifier
Dynamic: description
Dynamic: description-content-type
Dynamic: home-page
Dynamic: requires-python
Dynamic: summary
